nbmcp/cli.py
nbmcp/indexer.py
nbmcp/searcher.py
nbmcp/server.py
nbmcp-0.1.0.dist-info/METADATA
nbmcp-0.1.0.dist-info/WHEEL
nbmcp-0.1.0.dist-info/entry_points.txt
nbmcp-0.1.0.dist-info/RECORD
